{
  "2023-09-25": [
    {
      "desc": "Spinat mit 2 Spiegeleier und Kartoffeln (vegetarisch)",
      "price": 7.90
    },
    {
      "desc": "Frikadelle mit Letscho und Kartoffelpüree",
      "price": 7.90
    }
  ],
  "2023-09-26": [
    {
      "desc": "Spinat mit 2 Spiegeleier und Kartoffeln (vegetarisch)",
      "price": 7.90
    },
    {
      "desc": "Frikadelle mit Letscho und Kartoffelpüree",
      "price": 7.90
    }
  ],
  "2023-09-27": [
    {
      "desc": "Spinat mit 2 Spiegeleier und Kartoffeln (vegetarisch)",
      "price": 7.90
    },
    {
      "desc": "Frikadelle mit Letscho und Kartoffelpüree",
      "price": 7.90
    }
  ],
  "2023-09-28": [
    {
      "desc": "Spinat mit 2 Spiegeleier und Kartoffeln (vegetarisch)",
      "price": 7.90
    },
    {
      "desc": "Frikadelle mit Letscho und Kartoffelpüree",
      "price": 7.90
    }
  ],
  "2023-09-29": [
    {
      "desc": "Spinat mit 2 Spiegeleier und Kartoffeln (vegetarisch)",
      "price": 7.90
    },
    {
      "desc": "Frikadelle mit Letscho und Kartoffelpüree",
      "price": 7.90
    }
  ],
  "2023-10-02": [
    {
      "desc": "Spinat mit 2 Spiegeleier und Kartoffeln (vegetarisch)",
      "price": 7.90
    },
    {
      "desc": "Frikadelle mit Letscho und Kartoffelpüree",
      "price": 7.90
    }
  ],
  "2023-10-03": [
    {
      "desc": "Spinat mit 2 Spiegeleier und Kartoffeln (vegetarisch)",
      "price": 7.90
    },
    {
      "desc": "Frikadelle mit Letscho und Kartoffelpüree",
      "price": 7.90
    }
  ],
  "2023-10-04": [
    {
      "desc": "Spinat mit 2 Spiegeleier und Kartoffeln (vegetarisch)",
      "price": 7.90
    },
    {
      "desc": "Frikadelle mit Letscho und Kartoffelpüree",
      "price": 7.90
    }
  ],
  "2023-10-05": [
    {
      "desc": "Spinat mit 2 Spiegeleier und Kartoffeln (vegetarisch)",
      "price": 7.90
    },
    {
      "desc": "Frikadelle mit Letscho und Kartoffelpüree",
      "price": 7.90
    }
  ],
  "2023-10-06": [
    {
      "desc": "Spinat mit 2 Spiegeleier und Kartoffeln (vegetarisch)",
      "price": 7.90
    },
    {
      "desc": "Frikadelle mit Letscho und Kartoffelpüree",
      "price": 7.90
    }
  ]
}